gimoos_ddf/__init__.py
gimoos_ddf/create.py
gimoos_ddf/interface.py
gimoos_ddf/logger.py
gimoos_ddf/management.py
gimoos_ddf/template.py
gimoos_ddf/update.py
gimoos_ddf-0.8.2.dist-info/licenses/LICENSE
gimoos_ddf-0.8.2.dist-info/METADATA
gimoos_ddf-0.8.2.dist-info/WHEEL
gimoos_ddf-0.8.2.dist-info/entry_points.txt
gimoos_ddf-0.8.2.dist-info/top_level.txt
gimoos_ddf-0.8.2.dist-info/RECORD
