Metadata-Version: 2.4
Name: gimoos-ddf
Version: 0.8.2
Summary: 极墨思驱动开发框架
Author-email: one-ccs <one-ccs@foxmail.com>
Project-URL: homepage, https://github.com/one-ccs/gimoos_ddf
Requires-Python: >=3.12
License-File: LICENSE
Requires-Dist: aiohttp>=3.12.9
Requires-Dist: requests>=2.32.3
Requires-Dist: setuptools>=80.9.0
Requires-Dist: tqdm>=4.67.1
Requires-Dist: typing-extensions>=4.14.0
Requires-Dist: xknx>=3.8.0
Dynamic: license-file
